python_org_downloads/__init__.py
python_org_downloads/__main__.py
python_org_downloads/data/artifacts_kb.json
python_org_downloads-1.0.0.dist-info/licenses/LICENSE
python_org_downloads-1.0.0.dist-info/METADATA
python_org_downloads-1.0.0.dist-info/WHEEL
python_org_downloads-1.0.0.dist-info/top_level.txt
python_org_downloads-1.0.0.dist-info/RECORD
